pys3/__init__.py
pys3-0.0.1.dist-info/LICENSE
pys3-0.0.1.dist-info/METADATA
pys3-0.0.1.dist-info/WHEEL
pys3-0.0.1.dist-info/top_level.txt
pys3-0.0.1.dist-info/RECORD
